[
  {
    "label_idx": 0,
    "valid_execution": false,
    "source_contact_mask_12": [
      0,
      0,
      0,
      1,
      0,
      1,
      0,
      1,
      0,
      1,
      1,
      1
    ],
    "projected_physical_contact_mask_12": [
      0,
      0,
      0,
      1,
      1,
      1,
      0,
      0,
      0,
      0,
      0,
      0
    ],
    "projected_proximity_contact_mask_12": [
      0,
      0,
      0,
      1,
      1,
      1,
      1,
      0,
      0,
      0,
      0,
      0
    ],
    "projected_contact_mask_12": [
      0,
      0,
      0,
      1,
      1,
      1,
      1,
      0,
      0,
      0,
      0,
      0
    ],
    "projected_contact_distance_12_m": [
      0.010599353796263892,
      0.008608037228048591,
      0.012445697288982965,
      -0.00020206786321440122,
      -0.001414162542059027,
      -0.004957051850956429,
      0.004077202200476408,
      0.007387281567382646,
      0.02114608420186467,
      0.02262272797786776,
      0.025500000000000002,
      0.025500000000000002
    ],
    "projected_hold_object_drop_m": 0.24860992946524324,
    "projected_hold_hybrid_contact_group_count": 0.0,
    "projected_hold_hard_contact_group_count": 0.0,
    "projected_hold_has_thumb_opposition": 0.0,
    "projected_contact_group_count": 3.0,
    "projected_hard_contact_group_count": 2.0,
    "projected_has_thumb_opposition": 1.0,
    "projected_reach_object_facing_cos": 0.9517843959194876,
    "projected_reach_base_facing_cos": -0.3216521328955152,
    "projected_reach_downward_component": 0.5959045487650747,
    "projected_reach_min_arm_table_clearance_m": 0.3650384120995547,
    "projected_cylinder_palm_clearance_error_m": 0.0,
    "projected_cylinder_opposition_cos": -1.0,
    "projected_hold_cylinder_palm_clearance_error_m": 0.0,
    "projected_hold_cylinder_opposition_cos": -1.0,
    "projected_anchor_rmse_m": 0.07654149946155278,
    "projected_anchor_max_error_m": 0.09127726154596323,
    "projected_anchor_pairs": 5.0,
    "projected_anchor_assignment_norm_cost": 0.24402509972628295,
    "projected_anchor_assignment_method": 1.0,
    "retarget_method": "genhand_direct",
    "wrist_error_m": 0.0,
    "palm_error_m": 0.0,
    "tip_rmse_m": 0.0,
    "semantic_frame_error_deg": 0.0,
    "source_root_translation_gap_m": 0.03549374976204414,
    "source_wrist_error_m": 0.053806842613622244,
    "source_palm_error_m": 0.04980256283092925,
    "source_tip_rmse_m": 0.06025604525461445,
    "source_site_rmse_m": 0.05797712175037729,
    "source_semantic_frame_error_deg": 25.91187847775673,
    "source_contact_hamming": 6.0,
    "source_contact_misses": 4.0,
    "source_extra_contacts": 2.0,
    "projected_matched_target_contacts": 2.0,
    "projected_required_target_contacts": 2.0,
    "projected_hard_contact_count": 3.0,
    "projected_hybrid_contact_count": 4.0,
    "projected_min_contact_distance_m": -0.004957051850956429,
    "projected_total_penetration_m": 0.0,
    "projected_max_penetration_m": 0.0,
    "projected_object_translation_drift_m": 0.04678861933196966,
    "projected_object_rotation_drift_deg": 15.1148910230196,
    "projected_retreat_m": 0.010059242162426629,
    "projected_hand_open_blend": 0.30702618408222065,
    "projected_hold_object_translation_m": 0.25637160166535133,
    "projected_hold_object_rotation_deg": 26.690529672902386,
    "projected_hold_table_contact": 1.0,
    "projected_hold_matched_target_contacts": 0.0,
    "genhand_fc_loss": 0.0,
    "genhand_fc_net_wrench": 0.0,
    "genhand_fc_lin_ind": 0.9600459317747209,
    "genhand_fc_intfc": 0.0,
    "genhand_cluster_candidate_count": 66.0,
    "genhand_cluster_score_mean": 0.0076755002353453665,
    "genhand_target_anchor_rmse_m": 0.0012768000233180578,
    "projection_score": 11.152249568510596,
    "teacher_cost": 3.805391902863188,
    "optimizer_cost": 0.026904857652790902
  },
  {
    "label_idx": 1,
    "valid_execution": false,
    "source_contact_mask_12": [
      0,
      0,
      0,
      1,
      0,
      1,
      0,
      1,
      0,
      1,
      0,
      1
    ],
    "projected_physical_contact_mask_12": [
      0,
      0,
      0,
      1,
      1,
      1,
      0,
      1,
      0,
      1,
      0,
      0
    ],
    "projected_proximity_contact_mask_12": [
      0,
      0,
      0,
      1,
      1,
      1,
      1,
      1,
      0,
      1,
      0,
      0
    ],
    "projected_contact_mask_12": [
      0,
      0,
      0,
      1,
      1,
      1,
      1,
      1,
      0,
      1,
      0,
      0
    ],
    "projected_contact_distance_12_m": [
      0.025500000000000002,
      0.025500000000000002,
      0.018013686773355117,
      0.00043496884072541896,
      0.0008092350167101586,
      -0.009552777890503244,
      0.004609030669585356,
      -0.004683067018372675,
      0.013133864938527678,
      -0.006318930588715849,
      0.025500000000000002,
      0.00661534624453514
    ],
    "projected_hold_object_drop_m": 0.04477411107556001,
    "projected_hold_hybrid_contact_group_count": 3.0,
    "projected_hold_hard_contact_group_count": 3.0,
    "projected_hold_has_thumb_opposition": 0.0,
    "projected_contact_group_count": 4.0,
    "projected_hard_contact_group_count": 4.0,
    "projected_has_thumb_opposition": 1.0,
    "projected_reach_object_facing_cos": 0.9970391940709131,
    "projected_reach_base_facing_cos": 0.12202648044332703,
    "projected_reach_downward_component": 0.9058623024784392,
    "projected_reach_min_arm_table_clearance_m": 0.42200000000000004,
    "projected_cylinder_palm_clearance_error_m": 0.0,
    "projected_cylinder_opposition_cos": -1.0,
    "projected_hold_cylinder_palm_clearance_error_m": 0.0,
    "projected_hold_cylinder_opposition_cos": -1.0,
    "projected_anchor_rmse_m": 0.0718771384450476,
    "projected_anchor_max_error_m": 0.09528903629823485,
    "projected_anchor_pairs": 5.0,
    "projected_anchor_assignment_norm_cost": 0.24001553572664708,
    "projected_anchor_assignment_method": 1.0,
    "retarget_method": "genhand_direct",
    "wrist_error_m": 0.0,
    "palm_error_m": 0.0,
    "tip_rmse_m": 0.0,
    "semantic_frame_error_deg": 0.0,
    "source_root_translation_gap_m": 0.0354937488018059,
    "source_wrist_error_m": 0.028237182442715773,
    "source_palm_error_m": 0.03421139805544255,
    "source_tip_rmse_m": 0.07137976218691096,
    "source_site_rmse_m": 0.06261345186198405,
    "source_semantic_frame_error_deg": 45.243141636735785,
    "source_contact_hamming": 3.0,
    "source_contact_misses": 1.0,
    "source_extra_contacts": 2.0,
    "projected_matched_target_contacts": 4.0,
    "projected_required_target_contacts": 2.0,
    "projected_hard_contact_count": 5.0,
    "projected_hybrid_contact_count": 6.0,
    "projected_min_contact_distance_m": -0.009552777890503244,
    "projected_total_penetration_m": 0.014037185488698162,
    "projected_max_penetration_m": 0.00530260415334669,
    "projected_object_translation_drift_m": 0.04576838157295004,
    "projected_object_rotation_drift_deg": 5.443781690956967,
    "projected_retreat_m": 0.016648740394403165,
    "projected_hand_open_blend": 0.2257072071220864,
    "projected_hold_object_translation_m": 0.05064026724066277,
    "projected_hold_object_rotation_deg": 29.134821436446533,
    "projected_hold_table_contact": 0.0,
    "projected_hold_matched_target_contacts": 3.0,
    "genhand_fc_loss": 0.0,
    "genhand_fc_net_wrench": 0.0,
    "genhand_fc_lin_ind": 0.9314326563218347,
    "genhand_fc_intfc": 0.0,
    "genhand_cluster_candidate_count": 65.0,
    "genhand_cluster_score_mean": 0.006621477245272465,
    "genhand_target_anchor_rmse_m": 0.001615914436126759,
    "projection_score": 4.457174181938063,
    "teacher_cost": 2.964727658458645,
    "optimizer_cost": 0.004440622375013057
  },
  {
    "label_idx": 2,
    "valid_execution": false,
    "source_contact_mask_12": [
      0,
      0,
      0,
      1,
      0,
      1,
      0,
      1,
      0,
      1,
      0,
      1
    ],
    "projected_physical_contact_mask_12": [
      0,
      0,
      0,
      1,
      0,
      1,
      0,
      1,
      0,
      1,
      0,
      0
    ],
    "projected_proximity_contact_mask_12": [
      0,
      0,
      0,
      1,
      1,
      1,
      1,
      1,
      0,
      1,
      0,
      0
    ],
    "projected_contact_mask_12": [
      0,
      0,
      0,
      1,
      1,
      1,
      1,
      1,
      0,
      1,
      0,
      0
    ],
    "projected_contact_distance_12_m": [
      0.025500000000000002,
      0.018139000717023873,
      0.007603476406968463,
      0.00019049599637546537,
      0.00224458277306478,
      -0.007075248102567823,
      0.002679267193504642,
      -0.0062727757312612065,
      0.008726400115008536,
      -0.0005381073383474606,
      0.01791061448214289,
      0.005723253375758746
    ],
    "projected_hold_object_drop_m": 0.24837397178290332,
    "projected_hold_hybrid_contact_group_count": 0.0,
    "projected_hold_hard_contact_group_count": 0.0,
    "projected_hold_has_thumb_opposition": 0.0,
    "projected_contact_group_count": 4.0,
    "projected_hard_contact_group_count": 4.0,
    "projected_has_thumb_opposition": 1.0,
    "projected_reach_object_facing_cos": 0.997540898639452,
    "projected_reach_base_facing_cos": -0.049725994434445364,
    "projected_reach_downward_component": 0.8335213582627367,
    "projected_reach_min_arm_table_clearance_m": 0.42200000000000004,
    "projected_cylinder_palm_clearance_error_m": 0.0,
    "projected_cylinder_opposition_cos": -1.0,
    "projected_hold_cylinder_palm_clearance_error_m": 0.0,
    "projected_hold_cylinder_opposition_cos": -1.0,
    "projected_anchor_rmse_m": 0.04830521393772498,
    "projected_anchor_max_error_m": 0.07787265575456863,
    "projected_anchor_pairs": 5.0,
    "projected_anchor_assignment_norm_cost": 0.16133125305197815,
    "projected_anchor_assignment_method": 1.0,
    "retarget_method": "genhand_direct",
    "wrist_error_m": 0.0,
    "palm_error_m": 0.0,
    "tip_rmse_m": 0.0,
    "semantic_frame_error_deg": 0.0,
    "source_root_translation_gap_m": 0.03549375028492089,
    "source_wrist_error_m": 0.021788737294765582,
    "source_palm_error_m": 0.03874171656318946,
    "source_tip_rmse_m": 0.07242801388693546,
    "source_site_rmse_m": 0.06347637991882536,
    "source_semantic_frame_error_deg": 37.46561272250478,
    "source_contact_hamming": 3.0,
    "source_contact_misses": 1.0,
    "source_extra_contacts": 2.0,
    "projected_matched_target_contacts": 4.0,
    "projected_required_target_contacts": 2.0,
    "projected_hard_contact_count": 4.0,
    "projected_hybrid_contact_count": 6.0,
    "projected_min_contact_distance_m": -0.007075248102567823,
    "projected_total_penetration_m": 0.0,
    "projected_max_penetration_m": 0.0,
    "projected_object_translation_drift_m": 0.04092696268519575,
    "projected_object_rotation_drift_deg": 0.9856404360897418,
    "projected_retreat_m": 0.008526414528595604,
    "projected_hand_open_blend": 0.27081360194360155,
    "projected_hold_object_translation_m": 0.2701792597754475,
    "projected_hold_object_rotation_deg": 18.90135322520842,
    "projected_hold_table_contact": 1.0,
    "projected_hold_matched_target_contacts": 0.0,
    "genhand_fc_loss": 0.0,
    "genhand_fc_net_wrench": 0.0,
    "genhand_fc_lin_ind": 0.9403357872977857,
    "genhand_fc_intfc": 0.00416228405827943,
    "genhand_cluster_candidate_count": 63.0,
    "genhand_cluster_score_mean": 0.0028917361924671314,
    "genhand_target_anchor_rmse_m": 0.0013991079855251946,
    "projection_score": 10.79340051816339,
    "teacher_cost": 2.7217113590016537,
    "optimizer_cost": 0.004659625173735276
  },
  {
    "label_idx": 3,
    "valid_execution": false,
    "source_contact_mask_12": [
      0,
      0,
      0,
      1,
      0,
      1,
      0,
      1,
      0,
      1,
      0,
      1
    ],
    "projected_physical_contact_mask_12": [
      0,
      0,
      0,
      0,
      0,
      1,
      0,
      1,
      0,
      1,
      0,
      0
    ],
    "projected_proximity_contact_mask_12": [
      0,
      1,
      0,
      0,
      1,
      1,
      1,
      1,
      0,
      1,
      0,
      0
    ],
    "projected_contact_mask_12": [
      0,
      1,
      0,
      0,
      1,
      1,
      1,
      1,
      0,
      1,
      0,
      0
    ],
    "projected_contact_distance_12_m": [
      0.025500000000000002,
      0.002709128237457361,
      0.005061514596409216,
      0.004738866788747163,
      0.001574749066645959,
      -0.006500443294767873,
      0.0023307400202805147,
      -0.005543069583589911,
      0.008705566899709086,
      -0.0014101443633080801,
      0.02002132407858973,
      0.01575105626372636
    ],
    "projected_hold_object_drop_m": 0.023137167111870582,
    "projected_hold_hybrid_contact_group_count": 3.0,
    "projected_hold_hard_contact_group_count": 3.0,
    "projected_hold_has_thumb_opposition": 0.0,
    "projected_contact_group_count": 4.0,
    "projected_hard_contact_group_count": 3.0,
    "projected_has_thumb_opposition": 1.0,
    "projected_reach_object_facing_cos": 0.9754955535354539,
    "projected_reach_base_facing_cos": -0.35839979399841276,
    "projected_reach_downward_component": 0.6280661765427382,
    "projected_reach_min_arm_table_clearance_m": 0.38800798297206485,
    "projected_cylinder_palm_clearance_error_m": 0.0,
    "projected_cylinder_opposition_cos": -1.0,
    "projected_hold_cylinder_palm_clearance_error_m": 0.0,
    "projected_hold_cylinder_opposition_cos": -1.0,
    "projected_anchor_rmse_m": 0.049572885734810966,
    "projected_anchor_max_error_m": 0.07899308371925173,
    "projected_anchor_pairs": 5.0,
    "projected_anchor_assignment_norm_cost": 0.1385010368017336,
    "projected_anchor_assignment_method": 1.0,
    "retarget_method": "genhand_direct",
    "wrist_error_m": 0.0,
    "palm_error_m": 0.0,
    "tip_rmse_m": 0.0,
    "semantic_frame_error_deg": 0.0,
    "source_root_translation_gap_m": 0.03549374962864149,
    "source_wrist_error_m": 0.05203166379452665,
    "source_palm_error_m": 0.04252684681509231,
    "source_tip_rmse_m": 0.06755853042168129,
    "source_site_rmse_m": 0.062491830209975854,
    "source_semantic_frame_error_deg": 46.15324697355425,
    "source_contact_hamming": 5.0,
    "source_contact_misses": 2.0,
    "source_extra_contacts": 3.0,
    "projected_matched_target_contacts": 3.0,
    "projected_required_target_contacts": 2.0,
    "projected_hard_contact_count": 3.0,
    "projected_hybrid_contact_count": 6.0,
    "projected_min_contact_distance_m": -0.006500443294767873,
    "projected_total_penetration_m": 0.01497379960212442,
    "projected_max_penetration_m": 0.004722102729932518,
    "projected_object_translation_drift_m": 0.044118699638417386,
    "projected_object_rotation_drift_deg": 6.74734612242153,
    "projected_retreat_m": 0.01331048673076863,
    "projected_hand_open_blend": 0.25776716949868933,
    "projected_hold_object_translation_m": 0.025605397616415743,
    "projected_hold_object_rotation_deg": 37.398209588571795,
    "projected_hold_table_contact": 0.0,
    "projected_hold_matched_target_contacts": 3.0,
    "genhand_fc_loss": 0.0,
    "genhand_fc_net_wrench": 0.0,
    "genhand_fc_lin_ind": 0.9456059936988643,
    "genhand_fc_intfc": 0.0,
    "genhand_cluster_candidate_count": 57.0,
    "genhand_cluster_score_mean": 0.004082903017825104,
    "genhand_target_anchor_rmse_m": 0.00158154185264895,
    "projection_score": 4.509451600885853,
    "teacher_cost": 3.636721722843593,
    "optimizer_cost": 0.0037086149727816506
  },
  {
    "label_idx": 4,
    "valid_execution": false,
    "source_contact_mask_12": [
      0,
      0,
      0,
      1,
      0,
      1,
      0,
      1,
      0,
      1,
      0,
      1
    ],
    "projected_physical_contact_mask_12": [
      0,
      0,
      1,
      1,
      0,
      1,
      0,
      0,
      0,
      0,
      0,
      1
    ],
    "projected_proximity_contact_mask_12": [
      0,
      1,
      1,
      1,
      0,
      1,
      0,
      1,
      0,
      0,
      0,
      1
    ],
    "projected_contact_mask_12": [
      0,
      1,
      1,
      1,
      0,
      1,
      0,
      1,
      0,
      0,
      0,
      1
    ],
    "projected_contact_distance_12_m": [
      0.025500000000000002,
      0.002598098619081361,
      -0.011362587124187508,
      -0.01751487927513905,
      0.025500000000000002,
      0.0013237323679724054,
      0.023606435306758104,
      0.003818622298004128,
      0.02475893750300332,
      0.008133732728051625,
      0.021106958274739913,
      -0.0027598282798646182
    ],
    "projected_hold_object_drop_m": 0.01458293076812378,
    "projected_hold_hybrid_contact_group_count": 4.0,
    "projected_hold_hard_contact_group_count": 2.0,
    "projected_hold_has_thumb_opposition": 1.0,
    "projected_contact_group_count": 4.0,
    "projected_hard_contact_group_count": 3.0,
    "projected_has_thumb_opposition": 1.0,
    "projected_reach_object_facing_cos": 0.8882680396599545,
    "projected_reach_base_facing_cos": -0.5341600844931229,
    "projected_reach_downward_component": 0.4251147510185613,
    "projected_reach_min_arm_table_clearance_m": 0.34310395031696905,
    "projected_cylinder_palm_clearance_error_m": 0.0,
    "projected_cylinder_opposition_cos": -1.0,
    "projected_hold_cylinder_palm_clearance_error_m": 0.0,
    "projected_hold_cylinder_opposition_cos": -1.0,
    "projected_anchor_rmse_m": 0.09440722043810715,
    "projected_anchor_max_error_m": 0.10174873718932269,
    "projected_anchor_pairs": 4.0,
    "projected_anchor_assignment_norm_cost": 0.18364171378494226,
    "projected_anchor_assignment_method": 1.0,
    "retarget_method": "genhand_direct",
    "wrist_error_m": 0.0,
    "palm_error_m": 0.0,
    "tip_rmse_m": 0.0,
    "semantic_frame_error_deg": 0.0,
    "source_root_translation_gap_m": 0.035493748310372414,
    "source_wrist_error_m": 0.05378731658930701,
    "source_palm_error_m": 0.06152569438527148,
    "source_tip_rmse_m": 0.046534885159476264,
    "source_site_rmse_m": 0.0500085195305994,
    "source_semantic_frame_error_deg": 4.279583077516778,
    "source_contact_hamming": 3.0,
    "source_contact_misses": 1.0,
    "source_extra_contacts": 2.0,
    "projected_matched_target_contacts": 4.0,
    "projected_required_target_contacts": 2.0,
    "projected_hard_contact_count": 4.0,
    "projected_hybrid_contact_count": 6.0,
    "projected_min_contact_distance_m": -0.01751487927513905,
    "projected_total_penetration_m": 0.022831201733714883,
    "projected_max_penetration_m": 0.017684921132568435,
    "projected_object_translation_drift_m": 0.04782619726178106,
    "projected_object_rotation_drift_deg": 16.550657813451817,
    "projected_retreat_m": 0.0,
    "projected_hand_open_blend": 0.049461699713334494,
    "projected_hold_object_translation_m": 0.021230123885101492,
    "projected_hold_object_rotation_deg": 48.3333631846366,
    "projected_hold_table_contact": 0.0,
    "projected_hold_matched_target_contacts": 4.0,
    "genhand_fc_loss": 0.0,
    "genhand_fc_net_wrench": 0.0,
    "genhand_fc_lin_ind": 0.9762925478991781,
    "genhand_fc_intfc": 0.0,
    "genhand_cluster_candidate_count": 55.0,
    "genhand_cluster_score_mean": 0.0028989515777083407,
    "genhand_target_anchor_rmse_m": 0.001604559257326681,
    "projection_score": 4.248116516516789,
    "teacher_cost": Infinity,
    "optimizer_cost": 0.0017441406073274515
  },
  {
    "label_idx": 5,
    "valid_execution": false,
    "source_contact_mask_12": [
      0,
      0,
      0,
      1,
      0,
      1,
      0,
      1,
      0,
      1,
      0,
      0
    ],
    "projected_physical_contact_mask_12": [
      0,
      0,
      1,
      1,
      0,
      1,
      0,
      1,
      0,
      1,
      0,
      0
    ],
    "projected_proximity_contact_mask_12": [
      0,
      1,
      1,
      1,
      0,
      1,
      0,
      1,
      0,
      1,
      0,
      0
    ],
    "projected_contact_mask_12": [
      0,
      1,
      1,
      1,
      0,
      1,
      0,
      1,
      0,
      1,
      0,
      0
    ],
    "projected_contact_distance_12_m": [
      0.008258338294123941,
      0.003989690101854229,
      -0.0105838478669905,
      -0.01710221250463546,
      0.01196809122675073,
      -0.004374126787096215,
      0.014924900422806316,
      0.0005479982888369475,
      0.025500000000000002,
      0.00141658224836139,
      0.025500000000000002,
      0.020326493461011168
    ],
    "projected_hold_object_drop_m": 0.2907997331350503,
    "projected_hold_hybrid_contact_group_count": 0.0,
    "projected_hold_hard_contact_group_count": 0.0,
    "projected_hold_has_thumb_opposition": 0.0,
    "projected_contact_group_count": 4.0,
    "projected_hard_contact_group_count": 4.0,
    "projected_has_thumb_opposition": 1.0,
    "projected_reach_object_facing_cos": 0.8895776664548014,
    "projected_reach_base_facing_cos": -0.3022997227620508,
    "projected_reach_downward_component": 0.5583474898537711,
    "projected_reach_min_arm_table_clearance_m": 0.42200000000000004,
    "projected_cylinder_palm_clearance_error_m": 0.0,
    "projected_cylinder_opposition_cos": -1.0,
    "projected_hold_cylinder_palm_clearance_error_m": 0.0,
    "projected_hold_cylinder_opposition_cos": -1.0,
    "projected_anchor_rmse_m": 0.05017889046455456,
    "projected_anchor_max_error_m": 0.0548755584932329,
    "projected_anchor_pairs": 4.0,
    "projected_anchor_assignment_norm_cost": 0.22634784996041413,
    "projected_anchor_assignment_method": 1.0,
    "retarget_method": "genhand_direct",
    "wrist_error_m": 0.0,
    "palm_error_m": 0.0,
    "tip_rmse_m": 0.0,
    "semantic_frame_error_deg": 0.0,
    "source_root_translation_gap_m": 0.03549374980224287,
    "source_wrist_error_m": 0.04256719855751618,
    "source_palm_error_m": 0.04727296356995404,
    "source_tip_rmse_m": 0.058533485478696134,
    "source_site_rmse_m": 0.05500330391264156,
    "source_semantic_frame_error_deg": 2.434251728875746,
    "source_contact_hamming": 2.0,
    "source_contact_misses": 0.0,
    "source_extra_contacts": 2.0,
    "projected_matched_target_contacts": 4.0,
    "projected_required_target_contacts": 2.0,
    "projected_hard_contact_count": 5.0,
    "projected_hybrid_contact_count": 6.0,
    "projected_min_contact_distance_m": -0.01710221250463546,
    "projected_total_penetration_m": 0.0,
    "projected_max_penetration_m": 0.0,
    "projected_object_translation_drift_m": 0.04415187786132594,
    "projected_object_rotation_drift_deg": 20.444021878438065,
    "projected_retreat_m": 0.0,
    "projected_hand_open_blend": 0.0273586584425369,
    "projected_hold_object_translation_m": 0.30022219270666206,
    "projected_hold_object_rotation_deg": 94.40209710085485,
    "projected_hold_table_contact": 1.0,
    "projected_hold_matched_target_contacts": 0.0,
    "genhand_fc_loss": 0.0,
    "genhand_fc_net_wrench": 0.0,
    "genhand_fc_lin_ind": 0.977781641414561,
    "genhand_fc_intfc": 0.0,
    "genhand_cluster_candidate_count": 63.0,
    "genhand_cluster_score_mean": 0.008095113900342385,
    "genhand_target_anchor_rmse_m": 0.0014069365109214073,
    "projection_score": 15.212513453844704,
    "teacher_cost": Infinity,
    "optimizer_cost": 0.0016560104726755123
  },
  {
    "label_idx": 6,
    "valid_execution": false,
    "source_contact_mask_12": [
      0,
      0,
      0,
      1,
      0,
      1,
      0,
      1,
      0,
      1,
      0,
      0
    ],
    "projected_physical_contact_mask_12": [
      0,
      0,
      1,
      1,
      0,
      1,
      0,
      1,
      0,
      1,
      0,
      0
    ],
    "projected_proximity_contact_mask_12": [
      0,
      0,
      1,
      1,
      0,
      1,
      0,
      1,
      0,
      1,
      0,
      0
    ],
    "projected_contact_mask_12": [
      0,
      0,
      1,
      1,
      0,
      1,
      0,
      1,
      0,
      1,
      0,
      0
    ],
    "projected_contact_distance_12_m": [
      0.021253053142549373,
      0.009017759932665887,
      -0.009926841688620267,
      -0.015458399522171882,
      0.010566716495302844,
      -0.00036151801157661805,
      0.00961093747754144,
      -0.0007098891073875182,
      0.022496053159177982,
      -0.0036282347765275846,
      0.025500000000000002,
      0.010027289735503054
    ],
    "projected_hold_object_drop_m": 0.10466714445203856,
    "projected_hold_hybrid_contact_group_count": 0.0,
    "projected_hold_hard_contact_group_count": 0.0,
    "projected_hold_has_thumb_opposition": 0.0,
    "projected_contact_group_count": 4.0,
    "projected_hard_contact_group_count": 4.0,
    "projected_has_thumb_opposition": 1.0,
    "projected_reach_object_facing_cos": 0.8927278198084352,
    "projected_reach_base_facing_cos": -0.20573683983524715,
    "projected_reach_downward_component": 0.4476623341780686,
    "projected_reach_min_arm_table_clearance_m": 0.4167702366780843,
    "projected_cylinder_palm_clearance_error_m": 0.0,
    "projected_cylinder_opposition_cos": -1.0,
    "projected_hold_cylinder_palm_clearance_error_m": 0.0,
    "projected_hold_cylinder_opposition_cos": -1.0,
    "projected_anchor_rmse_m": 0.05480130469045461,
    "projected_anchor_max_error_m": 0.06188412498172916,
    "projected_anchor_pairs": 4.0,
    "projected_anchor_assignment_norm_cost": 0.20898509738749213,
    "projected_anchor_assignment_method": 1.0,
    "retarget_method": "genhand_direct",
    "wrist_error_m": 0.0,
    "palm_error_m": 0.0,
    "tip_rmse_m": 0.0,
    "semantic_frame_error_deg": 0.0,
    "source_root_translation_gap_m": 0.03549375247079158,
    "source_wrist_error_m": 0.0429006850502822,
    "source_palm_error_m": 0.03938448199873035,
    "source_tip_rmse_m": 0.04222937385629552,
    "source_site_rmse_m": 0.041932268995140416,
    "source_semantic_frame_error_deg": 4.066276505722001,
    "source_contact_hamming": 1.0,
    "source_contact_misses": 0.0,
    "source_extra_contacts": 1.0,
    "projected_matched_target_contacts": 4.0,
    "projected_required_target_contacts": 2.0,
    "projected_hard_contact_count": 5.0,
    "projected_hybrid_contact_count": 5.0,
    "projected_min_contact_distance_m": -0.015458399522171882,
    "projected_total_penetration_m": 0.0,
    "projected_max_penetration_m": 0.0,
    "projected_object_translation_drift_m": 0.033348810592165275,
    "projected_object_rotation_drift_deg": 23.07844578799725,
    "projected_retreat_m": 0.0,
    "projected_hand_open_blend": 0.0403924997854012,
    "projected_hold_object_translation_m": 0.11707895418495223,
    "projected_hold_object_rotation_deg": 133.33548137222007,
    "projected_hold_table_contact": 0.0,
    "projected_hold_matched_target_contacts": 0.0,
    "genhand_fc_loss": 0.0,
    "genhand_fc_net_wrench": 0.0,
    "genhand_fc_lin_ind": 0.9660939990412256,
    "genhand_fc_intfc": 0.0,
    "genhand_cluster_candidate_count": 56.0,
    "genhand_cluster_score_mean": 0.006282213282881592,
    "genhand_target_anchor_rmse_m": 0.0014952421939601007,
    "projection_score": 14.055156819230179,
    "teacher_cost": Infinity,
    "optimizer_cost": 0.0021218293766317414
  },
  {
    "label_idx": 7,
    "valid_execution": false,
    "source_contact_mask_12": [
      0,
      0,
      0,
      1,
      0,
      1,
      0,
      1,
      0,
      1,
      1,
      1
    ],
    "projected_physical_contact_mask_12": [
      0,
      0,
      0,
      1,
      0,
      0,
      0,
      0,
      0,
      0,
      0,
      0
    ],
    "projected_proximity_contact_mask_12": [
      1,
      0,
      0,
      1,
      0,
      0,
      0,
      0,
      0,
      0,
      0,
      0
    ],
    "projected_contact_mask_12": [
      1,
      0,
      0,
      1,
      0,
      0,
      0,
      0,
      0,
      0,
      0,
      0
    ],
    "projected_contact_distance_12_m": [
      0.00514031527923884,
      0.011509847298450915,
      0.012893485906642087,
      -0.0008199833437307642,
      0.007776851126225728,
      0.015121747316394056,
      0.013839677534461688,
      0.008560402820718734,
      0.022102716090554333,
      0.008862518974258356,
      0.025500000000000002,
      0.012746990314719828
    ],
    "projected_hold_object_drop_m": 0.24502624918195776,
    "projected_hold_hybrid_contact_group_count": 0.0,
    "projected_hold_hard_contact_group_count": 0.0,
    "projected_hold_has_thumb_opposition": 0.0,
    "projected_contact_group_count": 2.0,
    "projected_hard_contact_group_count": 1.0,
    "projected_has_thumb_opposition": 0.0,
    "projected_reach_object_facing_cos": 0.9517372720254965,
    "projected_reach_base_facing_cos": 0.04336988730911934,
    "projected_reach_downward_component": 0.8656301002099187,
    "projected_reach_min_arm_table_clearance_m": 0.42200000000000004,
    "projected_cylinder_palm_clearance_error_m": 0.0,
    "projected_cylinder_opposition_cos": -1.0,
    "projected_hold_cylinder_palm_clearance_error_m": 0.0,
    "projected_hold_cylinder_opposition_cos": -1.0,
    "projected_anchor_rmse_m": 0.04962313891169776,
    "projected_anchor_max_error_m": 0.07967908518664021,
    "projected_anchor_pairs": 5.0,
    "projected_anchor_assignment_norm_cost": 0.2605823564248356,
    "projected_anchor_assignment_method": 1.0,
    "retarget_method": "genhand_direct",
    "wrist_error_m": 0.0,
    "palm_error_m": 0.0,
    "tip_rmse_m": 0.0,
    "semantic_frame_error_deg": 0.0,
    "source_root_translation_gap_m": 0.03549374969752549,
    "source_wrist_error_m": 0.027007688772016484,
    "source_palm_error_m": 0.05479538516657022,
    "source_tip_rmse_m": 0.07649440267883721,
    "source_site_rmse_m": 0.06864912619807999,
    "source_semantic_frame_error_deg": 34.63901618734332,
    "source_contact_hamming": 6.0,
    "source_contact_misses": 5.0,
    "source_extra_contacts": 1.0,
    "projected_matched_target_contacts": 1.0,
    "projected_required_target_contacts": 2.0,
    "projected_hard_contact_count": 1.0,
    "projected_hybrid_contact_count": 2.0,
    "projected_min_contact_distance_m": -0.0008199833437307642,
    "projected_total_penetration_m": 0.0,
    "projected_max_penetration_m": 0.0,
    "projected_object_translation_drift_m": 0.04765548058129611,
    "projected_object_rotation_drift_deg": 7.6579843658676925,
    "projected_retreat_m": 0.003960297089703961,
    "projected_hand_open_blend": 0.45353032121637316,
    "projected_hold_object_translation_m": 0.2525424116891617,
    "projected_hold_object_rotation_deg": 12.48362506381168,
    "projected_hold_table_contact": 1.0,
    "projected_hold_matched_target_contacts": 0.0,
    "genhand_fc_loss": 0.0,
    "genhand_fc_net_wrench": 0.0,
    "genhand_fc_lin_ind": 0.9611277474857489,
    "genhand_fc_intfc": 0.0,
    "genhand_cluster_candidate_count": 67.0,
    "genhand_cluster_score_mean": 0.007807663408971387,
    "genhand_target_anchor_rmse_m": 0.0012732056134688386,
    "projection_score": 10.846516447814633,
    "teacher_cost": 3.6683808705296967,
    "optimizer_cost": 0.0030108737451503905
  },
  {
    "label_idx": 8,
    "valid_execution": false,
    "source_contact_mask_12": [
      0,
      0,
      0,
      1,
      0,
      1,
      0,
      1,
      0,
      1,
      0,
      1
    ],
    "projected_physical_contact_mask_12": [
      0,
      0,
      1,
      0,
      1,
      0,
      1,
      0,
      0,
      0,
      0,
      0
    ],
    "projected_proximity_contact_mask_12": [
      0,
      0,
      1,
      1,
      1,
      0,
      1,
      1,
      0,
      0,
      0,
      0
    ],
    "projected_contact_mask_12": [
      0,
      0,
      1,
      1,
      1,
      0,
      1,
      1,
      0,
      0,
      0,
      0
    ],
    "projected_contact_distance_12_m": [
      0.025500000000000002,
      0.017229937859461968,
      -0.0017749325490173358,
      0.0020870363767033686,
      0.0007048770133979681,
      0.00782033088284764,
      0.0007091046720691992,
      0.0028943663819619428,
      0.006933461687064602,
      0.008979715648772512,
      0.01443377591265484,
      0.018201719403879484
    ],
    "projected_hold_object_drop_m": 0.36718041533047524,
    "projected_hold_hybrid_contact_group_count": 0.0,
    "projected_hold_hard_contact_group_count": 0.0,
    "projected_hold_has_thumb_opposition": 0.0,
    "projected_contact_group_count": 3.0,
    "projected_hard_contact_group_count": 3.0,
    "projected_has_thumb_opposition": 1.0,
    "projected_reach_object_facing_cos": 0.9674951489776624,
    "projected_reach_base_facing_cos": -0.038990515168904394,
    "projected_reach_downward_component": 0.11568192300676837,
    "projected_reach_min_arm_table_clearance_m": 0.281330946992967,
    "projected_cylinder_palm_clearance_error_m": 0.0,
    "projected_cylinder_opposition_cos": -1.0,
    "projected_hold_cylinder_palm_clearance_error_m": 0.0,
    "projected_hold_cylinder_opposition_cos": -1.0,
    "projected_anchor_rmse_m": 0.04274393417616858,
    "projected_anchor_max_error_m": 0.04733619743130651,
    "projected_anchor_pairs": 5.0,
    "projected_anchor_assignment_norm_cost": 0.09960133153186035,
    "projected_anchor_assignment_method": 1.0,
    "retarget_method": "genhand_direct",
    "wrist_error_m": 0.0,
    "palm_error_m": 0.0,
    "tip_rmse_m": 0.0,
    "semantic_frame_error_deg": 0.0,
    "source_root_translation_gap_m": 0.03549374990726443,
    "source_wrist_error_m": 0.05620876836297277,
    "source_palm_error_m": 0.028281577925128285,
    "source_tip_rmse_m": 0.029100488922126477,
    "source_site_rmse_m": 0.0342124989030773,
    "source_semantic_frame_error_deg": 29.54360837940862,
    "source_contact_hamming": 6.0,
    "source_contact_misses": 3.0,
    "source_extra_contacts": 3.0,
    "projected_matched_target_contacts": 2.0,
    "projected_required_target_contacts": 2.0,
    "projected_hard_contact_count": 3.0,
    "projected_hybrid_contact_count": 5.0,
    "projected_min_contact_distance_m": -0.0017749325490173358,
    "projected_total_penetration_m": 0.0,
    "projected_max_penetration_m": 0.0,
    "projected_object_translation_drift_m": 0.01914020103499054,
    "projected_object_rotation_drift_deg": 9.536568997609644,
    "projected_retreat_m": 0.012025632809186252,
    "projected_hand_open_blend": 0.36400030383084087,
    "projected_hold_object_translation_m": 0.3741425833772259,
    "projected_hold_object_rotation_deg": 81.25427927254529,
    "projected_hold_table_contact": 1.0,
    "projected_hold_matched_target_contacts": 0.0,
    "genhand_fc_loss": 0.0,
    "genhand_fc_net_wrench": 0.0,
    "genhand_fc_lin_ind": 0.9445318596630583,
    "genhand_fc_intfc": 0.0,
    "genhand_cluster_candidate_count": 66.0,
    "genhand_cluster_score_mean": 0.0027660686527931633,
    "genhand_target_anchor_rmse_m": 0.0013482697517286204,
    "projection_score": 15.803848334505453,
    "teacher_cost": 3.674967123876547,
    "optimizer_cost": 0.0033821376551675026
  },
  {
    "label_idx": 9,
    "valid_execution": false,
    "source_contact_mask_12": [
      0,
      0,
      0,
      1,
      1,
      1,
      1,
      1,
      0,
      1,
      0,
      0
    ],
    "projected_physical_contact_mask_12": [
      1,
      1,
      0,
      1,
      0,
      0,
      0,
      0,
      0,
      0,
      0,
      0
    ],
    "projected_proximity_contact_mask_12": [
      1,
      1,
      1,
      1,
      0,
      0,
      0,
      0,
      0,
      0,
      0,
      0
    ],
    "projected_contact_mask_12": [
      1,
      1,
      1,
      1,
      0,
      0,
      0,
      0,
      0,
      0,
      0,
      0
    ],
    "projected_contact_distance_12_m": [
      -9.381300463261907e-05,
      -0.0004703111463173395,
      0.004244626144832653,
      -0.00377664431959345,
      0.007140935628530587,
      0.0076165271556524,
      0.02105669960473978,
      0.018054707369055765,
      0.025500000000000002,
      0.02114069757235123,
      0.025500000000000002,
      0.025500000000000002
    ],
    "projected_hold_object_drop_m": 0.24812543263505993,
    "projected_hold_hybrid_contact_group_count": 0.0,
    "projected_hold_hard_contact_group_count": 0.0,
    "projected_hold_has_thumb_opposition": 0.0,
    "projected_contact_group_count": 2.0,
    "projected_hard_contact_group_count": 2.0,
    "projected_has_thumb_opposition": 0.0,
    "projected_reach_object_facing_cos": 0.9825576925921614,
    "projected_reach_base_facing_cos": -0.23734311171632616,
    "projected_reach_downward_component": 0.5868851069446772,
    "projected_reach_min_arm_table_clearance_m": 0.3725962338886242,
    "projected_cylinder_palm_clearance_error_m": 0.0,
    "projected_cylinder_opposition_cos": -1.0,
    "projected_hold_cylinder_palm_clearance_error_m": 0.0,
    "projected_hold_cylinder_opposition_cos": -1.0,
    "projected_anchor_rmse_m": 0.04369485388843599,
    "projected_anchor_max_error_m": 0.0498355398584638,
    "projected_anchor_pairs": 4.0,
    "projected_anchor_assignment_norm_cost": 0.297739817084856,
    "projected_anchor_assignment_method": 1.0,
    "retarget_method": "genhand_direct",
    "wrist_error_m": 0.0,
    "palm_error_m": 0.0,
    "tip_rmse_m": 0.0,
    "semantic_frame_error_deg": 0.0,
    "source_root_translation_gap_m": 0.03549374858134633,
    "source_wrist_error_m": 0.041228632142293956,
    "source_palm_error_m": 0.06067839750510124,
    "source_tip_rmse_m": 0.07944087336066864,
    "source_site_rmse_m": 0.07263994359032643,
    "source_semantic_frame_error_deg": 12.764109844098549,
    "source_contact_hamming": 8.0,
    "source_contact_misses": 5.0,
    "source_extra_contacts": 3.0,
    "projected_matched_target_contacts": 1.0,
    "projected_required_target_contacts": 2.0,
    "projected_hard_contact_count": 3.0,
    "projected_hybrid_contact_count": 4.0,
    "projected_min_contact_distance_m": -0.00377664431959345,
    "projected_total_penetration_m": 0.0,
    "projected_max_penetration_m": 0.0,
    "projected_object_translation_drift_m": 0.06375875943600015,
    "projected_object_rotation_drift_deg": 15.250246290525155,
    "projected_retreat_m": 0.0,
    "projected_hand_open_blend": 0.07366918854892067,
    "projected_hold_object_translation_m": 0.29105811947936466,
    "projected_hold_object_rotation_deg": 22.445786703662222,
    "projected_hold_table_contact": 1.0,
    "projected_hold_matched_target_contacts": 0.0,
    "genhand_fc_loss": 0.0,
    "genhand_fc_net_wrench": 0.0,
    "genhand_fc_lin_ind": 0.9701049080158637,
    "genhand_fc_intfc": 0.0,
    "genhand_cluster_candidate_count": 50.0,
    "genhand_cluster_score_mean": 0.007455529258874985,
    "genhand_target_anchor_rmse_m": 0.0010918342448214583,
    "projection_score": 11.483759952994767,
    "teacher_cost": Infinity,
    "optimizer_cost": 0.003059479315066075
  },
  {
    "label_idx": 10,
    "valid_execution": false,
    "source_contact_mask_12": [
      0,
      0,
      0,
      1,
      0,
      1,
      0,
      1,
      0,
      1,
      0,
      1
    ],
    "projected_physical_contact_mask_12": [
      0,
      0,
      0,
      1,
      1,
      1,
      0,
      0,
      0,
      0,
      0,
      0
    ],
    "projected_proximity_contact_mask_12": [
      0,
      1,
      1,
      1,
      1,
      1,
      1,
      1,
      0,
      0,
      0,
      0
    ],
    "projected_contact_mask_12": [
      0,
      1,
      1,
      1,
      1,
      1,
      1,
      1,
      0,
      0,
      0,
      0
    ],
    "projected_contact_distance_12_m": [
      0.018921432380290135,
      0.0029219392179814577,
      0.0015747399457640724,
      -0.005066517542884027,
      -0.004489928238589362,
      -0.006717334286689176,
      0.0036190780816634117,
      0.003131167786012654,
      0.021105938014576574,
      0.021824760365104043,
      0.025500000000000002,
      0.025500000000000002
    ],
    "projected_hold_object_drop_m": 0.24644106293057194,
    "projected_hold_hybrid_contact_group_count": 0.0,
    "projected_hold_hard_contact_group_count": 0.0,
    "projected_hold_has_thumb_opposition": 0.0,
    "projected_contact_group_count": 3.0,
    "projected_hard_contact_group_count": 2.0,
    "projected_has_thumb_opposition": 1.0,
    "projected_reach_object_facing_cos": 0.9715406626915767,
    "projected_reach_base_facing_cos": -0.3115398242693668,
    "projected_reach_downward_component": 0.6395656923393827,
    "projected_reach_min_arm_table_clearance_m": 0.4061919647478025,
    "projected_cylinder_palm_clearance_error_m": 0.0,
    "projected_cylinder_opposition_cos": -1.0,
    "projected_hold_cylinder_palm_clearance_error_m": 0.0,
    "projected_hold_cylinder_opposition_cos": -1.0,
    "projected_anchor_rmse_m": 0.04832493262973571,
    "projected_anchor_max_error_m": 0.06757965735701241,
    "projected_anchor_pairs": 5.0,
    "projected_anchor_assignment_norm_cost": 0.20428077934948236,
    "projected_anchor_assignment_method": 1.0,
    "retarget_method": "genhand_direct",
    "wrist_error_m": 0.0,
    "palm_error_m": 0.0,
    "tip_rmse_m": 0.0,
    "semantic_frame_error_deg": 0.0,
    "source_root_translation_gap_m": 0.03549374906531116,
    "source_wrist_error_m": 0.054216896038248606,
    "source_palm_error_m": 0.04182426238391295,
    "source_tip_rmse_m": 0.05660600468198614,
    "source_site_rmse_m": 0.05439267226154883,
    "source_semantic_frame_error_deg": 29.399914739852235,
    "source_contact_hamming": 6.0,
    "source_contact_misses": 2.0,
    "source_extra_contacts": 4.0,
    "projected_matched_target_contacts": 3.0,
    "projected_required_target_contacts": 2.0,
    "projected_hard_contact_count": 3.0,
    "projected_hybrid_contact_count": 7.0,
    "projected_min_contact_distance_m": -0.006717334286689176,
    "projected_total_penetration_m": 0.0,
    "projected_max_penetration_m": 0.0,
    "projected_object_translation_drift_m": 0.04042372530521589,
    "projected_object_rotation_drift_deg": 4.61095741013946,
    "projected_retreat_m": 0.006564771497912189,
    "projected_hand_open_blend": 0.3425152582616906,
    "projected_hold_object_translation_m": 0.2663044837592227,
    "projected_hold_object_rotation_deg": 35.75394618754584,
    "projected_hold_table_contact": 1.0,
    "projected_hold_matched_target_contacts": 0.0,
    "genhand_fc_loss": 0.0,
    "genhand_fc_net_wrench": 0.0,
    "genhand_fc_lin_ind": 0.965275741224251,
    "genhand_fc_intfc": 0.0,
    "genhand_cluster_candidate_count": 66.0,
    "genhand_cluster_score_mean": 0.006800007378299587,
    "genhand_target_anchor_rmse_m": 0.001424933468064643,
    "projection_score": 11.59211778258377,
    "teacher_cost": 4.000281431822882,
    "optimizer_cost": 0.0015494389270041765
  },
  {
    "label_idx": 11,
    "valid_execution": false,
    "source_contact_mask_12": [
      0,
      0,
      0,
      1,
      0,
      1,
      0,
      1,
      0,
      1,
      0,
      1
    ],
    "projected_physical_contact_mask_12": [
      0,
      0,
      1,
      1,
      0,
      0,
      0,
      0,
      0,
      0,
      0,
      0
    ],
    "projected_proximity_contact_mask_12": [
      0,
      1,
      1,
      1,
      0,
      1,
      0,
      0,
      0,
      0,
      0,
      0
    ],
    "projected_contact_mask_12": [
      0,
      1,
      1,
      1,
      0,
      1,
      0,
      0,
      0,
      0,
      0,
      0
    ],
    "projected_contact_distance_12_m": [
      0.025500000000000002,
      0.003134075863211048,
      0.00014096266014635133,
      -0.0017374344274655954,
      0.01015888758420223,
      0.0016041554571635773,
      0.0063719394830646595,
      0.004739394943847167,
      0.014059770939702176,
      0.015355905641317424,
      0.025216189170711542,
      0.025500000000000002
    ],
    "projected_hold_object_drop_m": 0.2463238709371951,
    "projected_hold_hybrid_contact_group_count": 0.0,
    "projected_hold_hard_contact_group_count": 0.0,
    "projected_hold_has_thumb_opposition": 0.0,
    "projected_contact_group_count": 2.0,
    "projected_hard_contact_group_count": 1.0,
    "projected_has_thumb_opposition": 1.0,
    "projected_reach_object_facing_cos": 0.96892974072207,
    "projected_reach_base_facing_cos": -0.041332011381973455,
    "projected_reach_downward_component": 0.7111978101968169,
    "projected_reach_min_arm_table_clearance_m": 0.3946518889512971,
    "projected_cylinder_palm_clearance_error_m": 0.0,
    "projected_cylinder_opposition_cos": -1.0,
    "projected_hold_cylinder_palm_clearance_error_m": 0.0,
    "projected_hold_cylinder_opposition_cos": -1.0,
    "projected_anchor_rmse_m": 0.09505062960477001,
    "projected_anchor_max_error_m": 0.10380307584290292,
    "projected_anchor_pairs": 5.0,
    "projected_anchor_assignment_norm_cost": 0.10006053934291485,
    "projected_anchor_assignment_method": 1.0,
    "retarget_method": "genhand_direct",
    "wrist_error_m": 0.0,
    "palm_error_m": 0.0,
    "tip_rmse_m": 0.0,
    "semantic_frame_error_deg": 0.0,
    "source_root_translation_gap_m": 0.03549375001545962,
    "source_wrist_error_m": 0.018635257623395504,
    "source_palm_error_m": 0.05065852330829846,
    "source_tip_rmse_m": 0.061601821038562515,
    "source_site_rmse_m": 0.055917644272375056,
    "source_semantic_frame_error_deg": 27.90678299021119,
    "source_contact_hamming": 5.0,
    "source_contact_misses": 3.0,
    "source_extra_contacts": 2.0,
    "projected_matched_target_contacts": 2.0,
    "projected_required_target_contacts": 2.0,
    "projected_hard_contact_count": 2.0,
    "projected_hybrid_contact_count": 4.0,
    "projected_min_contact_distance_m": -0.0017374344274655954,
    "projected_total_penetration_m": 0.0,
    "projected_max_penetration_m": 0.0,
    "projected_object_translation_drift_m": 0.0610251667666072,
    "projected_object_rotation_drift_deg": 12.808312540142538,
    "projected_retreat_m": 0.01778068840836064,
    "projected_hand_open_blend": 0.3516819536667667,
    "projected_hold_object_translation_m": 0.27211469206284,
    "projected_hold_object_rotation_deg": 3.076686715113738,
    "projected_hold_table_contact": 1.0,
    "projected_hold_matched_target_contacts": 0.0,
    "genhand_fc_loss": 0.0,
    "genhand_fc_net_wrench": 0.0,
    "genhand_fc_lin_ind": 0.9497819228438356,
    "genhand_fc_intfc": 0.0,
    "genhand_cluster_candidate_count": 67.0,
    "genhand_cluster_score_mean": 0.00549147319604695,
    "genhand_target_anchor_rmse_m": 0.0008373871904396653,
    "projection_score": 9.994311520206937,
    "teacher_cost": 4.161875871479869,
    "optimizer_cost": 0.0024902211908910065
  },
  {
    "label_idx": 12,
    "valid_execution": false,
    "source_contact_mask_12": [
      0,
      0,
      0,
      1,
      0,
      1,
      0,
      1,
      0,
      1,
      0,
      1
    ],
    "projected_physical_contact_mask_12": [
      0,
      0,
      0,
      1,
      0,
      0,
      0,
      0,
      0,
      0,
      0,
      0
    ],
    "projected_proximity_contact_mask_12": [
      0,
      0,
      0,
      1,
      0,
      0,
      0,
      0,
      0,
      0,
      0,
      0
    ],
    "projected_contact_mask_12": [
      0,
      0,
      0,
      1,
      0,
      0,
      0,
      0,
      0,
      0,
      0,
      0
    ],
    "projected_contact_distance_12_m": [
      0.013078930252778587,
      0.015722808236165384,
      0.012272076681087297,
      -0.0009944625000593479,
      0.007951307658868038,
      0.015670122144751344,
      0.017215587231218726,
      0.019799236671047594,
      0.025500000000000002,
      0.02322142802191572,
      0.025500000000000002,
      0.023230460291893004
    ],
    "projected_hold_object_drop_m": 0.2489074047768866,
    "projected_hold_hybrid_contact_group_count": 0.0,
    "projected_hold_hard_contact_group_count": 0.0,
    "projected_hold_has_thumb_opposition": 0.0,
    "projected_contact_group_count": 1.0,
    "projected_hard_contact_group_count": 1.0,
    "projected_has_thumb_opposition": 0.0,
    "projected_reach_object_facing_cos": 0.9264886173515826,
    "projected_reach_base_facing_cos": 0.27197596973128,
    "projected_reach_downward_component": 0.9282384439140612,
    "projected_reach_min_arm_table_clearance_m": 0.42200000000000004,
    "projected_cylinder_palm_clearance_error_m": 0.0,
    "projected_cylinder_opposition_cos": -1.0,
    "projected_hold_cylinder_palm_clearance_error_m": 0.0,
    "projected_hold_cylinder_opposition_cos": -1.0,
    "projected_anchor_rmse_m": 0.0999327129735633,
    "projected_anchor_max_error_m": 0.11482653253404196,
    "projected_anchor_pairs": 5.0,
    "projected_anchor_assignment_norm_cost": 0.33480351934344615,
    "projected_anchor_assignment_method": 1.0,
    "retarget_method": "genhand_direct",
    "wrist_error_m": 0.0,
    "palm_error_m": 0.0,
    "tip_rmse_m": 0.0,
    "semantic_frame_error_deg": 0.0,
    "source_root_translation_gap_m": 0.03549375038028111,
    "source_wrist_error_m": 0.040878232463623584,
    "source_palm_error_m": 0.06278893837302141,
    "source_tip_rmse_m": 0.08266871002576606,
    "source_site_rmse_m": 0.07538857317542239,
    "source_semantic_frame_error_deg": 48.159311830429544,
    "source_contact_hamming": 4.0,
    "source_contact_misses": 4.0,
    "source_extra_contacts": 0.0,
    "projected_matched_target_contacts": 1.0,
    "projected_required_target_contacts": 2.0,
    "projected_hard_contact_count": 1.0,
    "projected_hybrid_contact_count": 1.0,
    "projected_min_contact_distance_m": -0.0009944625000593479,
    "projected_total_penetration_m": 0.0,
    "projected_max_penetration_m": 0.0,
    "projected_object_translation_drift_m": 0.03749022018284333,
    "projected_object_rotation_drift_deg": 16.435639973763955,
    "projected_retreat_m": 0.0026215437379395437,
    "projected_hand_open_blend": 0.43001420593878653,
    "projected_hold_object_translation_m": 0.2515437671684124,
    "projected_hold_object_rotation_deg": 30.31797366724563,
    "projected_hold_table_contact": 1.0,
    "projected_hold_matched_target_contacts": 0.0,
    "genhand_fc_loss": 0.0,
    "genhand_fc_net_wrench": 0.0,
    "genhand_fc_lin_ind": 0.9497527113334279,
    "genhand_fc_intfc": 0.0,
    "genhand_cluster_candidate_count": 62.0,
    "genhand_cluster_score_mean": 0.005303684488016569,
    "genhand_target_anchor_rmse_m": 0.001438296476579688,
    "projection_score": 12.343092648017528,
    "teacher_cost": 2.8978383830737924,
    "optimizer_cost": 0.0015810428409234775
  },
  {
    "label_idx": 13,
    "valid_execution": false,
    "source_contact_mask_12": [
      0,
      0,
      0,
      1,
      0,
      1,
      0,
      1,
      0,
      1,
      0,
      1
    ],
    "projected_physical_contact_mask_12": [
      0,
      0,
      1,
      1,
      0,
      1,
      0,
      1,
      0,
      0,
      0,
      0
    ],
    "projected_proximity_contact_mask_12": [
      0,
      0,
      1,
      1,
      0,
      1,
      0,
      1,
      0,
      0,
      0,
      0
    ],
    "projected_contact_mask_12": [
      0,
      0,
      1,
      1,
      0,
      1,
      0,
      1,
      0,
      0,
      0,
      0
    ],
    "projected_contact_distance_12_m": [
      0.025500000000000002,
      0.017509589439899505,
      0.00020222268475208246,
      0.000887912048461002,
      0.02268369716110352,
      -0.010717087924422015,
      0.015913478868358536,
      -0.004024061754693564,
      0.0163920222192487,
      0.007934070900082779,
      0.025500000000000002,
      0.021474220532445763
    ],
    "projected_hold_object_drop_m": 0.25300503022260135,
    "projected_hold_hybrid_contact_group_count": 0.0,
    "projected_hold_hard_contact_group_count": 0.0,
    "projected_hold_has_thumb_opposition": 0.0,
    "projected_contact_group_count": 3.0,
    "projected_hard_contact_group_count": 3.0,
    "projected_has_thumb_opposition": 1.0,
    "projected_reach_object_facing_cos": 0.9528123800348574,
    "projected_reach_base_facing_cos": 0.07303479394779833,
    "projected_reach_downward_component": 0.7094221894132856,
    "projected_reach_min_arm_table_clearance_m": 0.4128915399973213,
    "projected_cylinder_palm_clearance_error_m": 0.0,
    "projected_cylinder_opposition_cos": -1.0,
    "projected_hold_cylinder_palm_clearance_error_m": 0.0,
    "projected_hold_cylinder_opposition_cos": -1.0,
    "projected_anchor_rmse_m": 0.06747689539712211,
    "projected_anchor_max_error_m": 0.07851736769386736,
    "projected_anchor_pairs": 5.0,
    "projected_anchor_assignment_norm_cost": 0.1999236449813247,
    "projected_anchor_assignment_method": 1.0,
    "retarget_method": "genhand_direct",
    "wrist_error_m": 0.0,
    "palm_error_m": 0.0,
    "tip_rmse_m": 0.0,
    "semantic_frame_error_deg": 0.0,
    "source_root_translation_gap_m": 0.03549374921528752,
    "source_wrist_error_m": 0.036026130262656476,
    "source_palm_error_m": 0.033241372660091494,
    "source_tip_rmse_m": 0.04248475404373476,
    "source_site_rmse_m": 0.04040445970578028,
    "source_semantic_frame_error_deg": 18.078037099490352,
    "source_contact_hamming": 3.0,
    "source_contact_misses": 2.0,
    "source_extra_contacts": 1.0,
    "projected_matched_target_contacts": 3.0,
    "projected_required_target_contacts": 2.0,
    "projected_hard_contact_count": 4.0,
    "projected_hybrid_contact_count": 4.0,
    "projected_min_contact_distance_m": -0.010717087924422015,
    "projected_total_penetration_m": 0.0,
    "projected_max_penetration_m": 0.0,
    "projected_object_translation_drift_m": 0.03321788940553942,
    "projected_object_rotation_drift_deg": 8.24442098895825,
    "projected_retreat_m": 0.022417179968089423,
    "projected_hand_open_blend": 0.2743839744332232,
    "projected_hold_object_translation_m": 0.25644818183235263,
    "projected_hold_object_rotation_deg": 10.940042507914066,
    "projected_hold_table_contact": 1.0,
    "projected_hold_matched_target_contacts": 0.0,
    "genhand_fc_loss": 0.0,
    "genhand_fc_net_wrench": 0.0,
    "genhand_fc_lin_ind": 0.926701927756527,
    "genhand_fc_intfc": 0.0,
    "genhand_cluster_candidate_count": 64.0,
    "genhand_cluster_score_mean": 0.008424142443265384,
    "genhand_target_anchor_rmse_m": 0.0015605855980650785,
    "projection_score": 10.378105125419161,
    "teacher_cost": 2.8695925276616285,
    "optimizer_cost": 0.002453841260365536
  },
  {
    "label_idx": 14,
    "valid_execution": false,
    "source_contact_mask_12": [
      0,
      0,
      0,
      1,
      0,
      1,
      0,
      1,
      0,
      1,
      0,
      0
    ],
    "projected_physical_contact_mask_12": [
      0,
      0,
      0,
      0,
      0,
      0,
      0,
      1,
      0,
      1,
      0,
      0
    ],
    "projected_proximity_contact_mask_12": [
      0,
      0,
      1,
      1,
      0,
      0,
      0,
      1,
      0,
      1,
      0,
      0
    ],
    "projected_contact_mask_12": [
      0,
      0,
      1,
      1,
      0,
      0,
      0,
      1,
      0,
      1,
      0,
      0
    ],
    "projected_contact_distance_12_m": [
      0.025500000000000002,
      0.005614656263146429,
      0.0022773540945553823,
      0.0035208147121514616,
      0.025500000000000002,
      0.018933697942107308,
      0.025500000000000002,
      -0.0052519823057673035,
      0.022481705567467872,
      -0.008789964459109146,
      0.025500000000000002,
      0.013366333429909052
    ],
    "projected_hold_object_drop_m": 0.24070057134955875,
    "projected_hold_hybrid_contact_group_count": 0.0,
    "projected_hold_hard_contact_group_count": 0.0,
    "projected_hold_has_thumb_opposition": 0.0,
    "projected_contact_group_count": 3.0,
    "projected_hard_contact_group_count": 2.0,
    "projected_has_thumb_opposition": 1.0,
    "projected_reach_object_facing_cos": 0.8240006420496797,
    "projected_reach_base_facing_cos": -0.11738108548417334,
    "projected_reach_downward_component": 0.4640707539896721,
    "projected_reach_min_arm_table_clearance_m": 0.3106145316645301,
    "projected_cylinder_palm_clearance_error_m": 0.0,
    "projected_cylinder_opposition_cos": -1.0,
    "projected_hold_cylinder_palm_clearance_error_m": 0.0,
    "projected_hold_cylinder_opposition_cos": -1.0,
    "projected_anchor_rmse_m": 0.08479477741416092,
    "projected_anchor_max_error_m": 0.09629496052431047,
    "projected_anchor_pairs": 3.0,
    "projected_anchor_assignment_norm_cost": 0.104086851638398,
    "projected_anchor_assignment_method": 1.0,
    "retarget_method": "genhand_direct",
    "wrist_error_m": 0.0,
    "palm_error_m": 0.0,
    "tip_rmse_m": 0.0,
    "semantic_frame_error_deg": 0.0,
    "source_root_translation_gap_m": 0.03549374737906384,
    "source_wrist_error_m": 0.04178514462360972,
    "source_palm_error_m": 0.0448345842066168,
    "source_tip_rmse_m": 0.05418376038758389,
    "source_site_rmse_m": 0.051319082639740665,
    "source_semantic_frame_error_deg": 3.8195306724484723,
    "source_contact_hamming": 2.0,
    "source_contact_misses": 1.0,
    "source_extra_contacts": 1.0,
    "projected_matched_target_contacts": 3.0,
    "projected_required_target_contacts": 2.0,
    "projected_hard_contact_count": 2.0,
    "projected_hybrid_contact_count": 4.0,
    "projected_min_contact_distance_m": -0.008789964459109146,
    "projected_total_penetration_m": 0.0,
    "projected_max_penetration_m": 0.0,
    "projected_object_translation_drift_m": 0.024765554773075585,
    "projected_object_rotation_drift_deg": 18.438647126579617,
    "projected_retreat_m": 0.0,
    "projected_hand_open_blend": 0.04674055169312435,
    "projected_hold_object_translation_m": 0.25713985879693163,
    "projected_hold_object_rotation_deg": 75.70615417860266,
    "projected_hold_table_contact": 1.0,
    "projected_hold_matched_target_contacts": 0.0,
    "genhand_fc_loss": 0.0,
    "genhand_fc_net_wrench": 0.0,
    "genhand_fc_lin_ind": 0.9730974784246506,
    "genhand_fc_intfc": 0.0,
    "genhand_cluster_candidate_count": 45.0,
    "genhand_cluster_score_mean": 0.007394558163540034,
    "genhand_target_anchor_rmse_m": 0.0008362352394147168,
    "projection_score": 13.434100143990912,
    "teacher_cost": Infinity,
    "optimizer_cost": 0.0024173386471587634
  },
  {
    "label_idx": 15,
    "valid_execution": false,
    "source_contact_mask_12": [
      0,
      0,
      0,
      1,
      0,
      1,
      0,
      1,
      0,
      1,
      0,
      1
    ],
    "projected_physical_contact_mask_12": [
      0,
      0,
      0,
      1,
      0,
      0,
      0,
      0,
      0,
      0,
      0,
      0
    ],
    "projected_proximity_contact_mask_12": [
      0,
      0,
      0,
      1,
      0,
      0,
      0,
      1,
      0,
      1,
      0,
      0
    ],
    "projected_contact_mask_12": [
      0,
      0,
      0,
      1,
      0,
      0,
      0,
      1,
      0,
      1,
      0,
      0
    ],
    "projected_contact_distance_12_m": [
      0.025500000000000002,
      0.025500000000000002,
      0.02228702193086891,
      0.0009759517019245437,
      0.014846248361224026,
      0.014136671439767276,
      0.0188939184842675,
      0.002289765767639277,
      0.025500000000000002,
      0.0028888499861413775,
      0.025500000000000002,
      0.021075531968538515
    ],
    "projected_hold_object_drop_m": 0.3153123316330027,
    "projected_hold_hybrid_contact_group_count": 0.0,
    "projected_hold_hard_contact_group_count": 0.0,
    "projected_hold_has_thumb_opposition": 0.0,
    "projected_contact_group_count": 3.0,
    "projected_hard_contact_group_count": 1.0,
    "projected_has_thumb_opposition": 1.0,
    "projected_reach_object_facing_cos": 0.8535742374072376,
    "projected_reach_base_facing_cos": -0.22309594761185564,
    "projected_reach_downward_component": 0.6779087778740187,
    "projected_reach_min_arm_table_clearance_m": 0.3994091160842028,
    "projected_cylinder_palm_clearance_error_m": 0.0,
    "projected_cylinder_opposition_cos": -1.0,
    "projected_hold_cylinder_palm_clearance_error_m": 0.0,
    "projected_hold_cylinder_opposition_cos": -1.0,
    "projected_anchor_rmse_m": 0.11577840937661531,
    "projected_anchor_max_error_m": 0.12664033315114512,
    "projected_anchor_pairs": 5.0,
    "projected_anchor_assignment_norm_cost": 0.23616262833313817,
    "projected_anchor_assignment_method": 1.0,
    "retarget_method": "genhand_direct",
    "wrist_error_m": 0.0,
    "palm_error_m": 0.0,
    "tip_rmse_m": 0.0,
    "semantic_frame_error_deg": 0.0,
    "source_root_translation_gap_m": 0.03549375118928128,
    "source_wrist_error_m": 0.0497876227571961,
    "source_palm_error_m": 0.06889680363096266,
    "source_tip_rmse_m": 0.08982322035721985,
    "source_site_rmse_m": 0.08243320370118262,
    "source_semantic_frame_error_deg": 35.15425205433753,
    "source_contact_hamming": 2.0,
    "source_contact_misses": 2.0,
    "source_extra_contacts": 0.0,
    "projected_matched_target_contacts": 3.0,
    "projected_required_target_contacts": 2.0,
    "projected_hard_contact_count": 1.0,
    "projected_hybrid_contact_count": 3.0,
    "projected_min_contact_distance_m": 0.0009759517019245437,
    "projected_total_penetration_m": 0.0,
    "projected_max_penetration_m": 0.0,
    "projected_object_translation_drift_m": 0.046680558720033294,
    "projected_object_rotation_drift_deg": 12.024938137463595,
    "projected_retreat_m": 0.011009354637180826,
    "projected_hand_open_blend": 0.3406338351621511,
    "projected_hold_object_translation_m": 0.3241395470340477,
    "projected_hold_object_rotation_deg": 90.53492432009016,
    "projected_hold_table_contact": 1.0,
    "projected_hold_matched_target_contacts": 0.0,
    "genhand_fc_loss": 0.0,
    "genhand_fc_net_wrench": 0.0,
    "genhand_fc_lin_ind": 0.9587048954892594,
    "genhand_fc_intfc": 0.0,
    "genhand_cluster_candidate_count": 64.0,
    "genhand_cluster_score_mean": 0.006297506530360652,
    "genhand_target_anchor_rmse_m": 0.001214506420310477,
    "projection_score": 15.483456372461783,
    "teacher_cost": 2.8126835248462143,
    "optimizer_cost": 0.0014465277369843444
  },
  {
    "label_idx": 16,
    "valid_execution": false,
    "source_contact_mask_12": [
      0,
      0,
      0,
      1,
      0,
      1,
      0,
      1,
      0,
      1,
      0,
      1
    ],
    "projected_physical_contact_mask_12": [
      0,
      1,
      0,
      0,
      0,
      0,
      0,
      0,
      0,
      0,
      0,
      0
    ],
    "projected_proximity_contact_mask_12": [
      1,
      1,
      0,
      1,
      0,
      1,
      0,
      1,
      0,
      0,
      0,
      0
    ],
    "projected_contact_mask_12": [
      1,
      1,
      0,
      1,
      0,
      1,
      0,
      1,
      0,
      0,
      0,
      0
    ],
    "projected_contact_distance_12_m": [
      0.004603689013694932,
      -0.0007836524899173299,
      0.008379602997915962,
      0.0017060456946829273,
      0.005970722760579329,
      0.003632534605168722,
      0.015847068469527364,
      0.0033141883754467345,
      0.025500000000000002,
      0.009982713751044864,
      0.025500000000000002,
      0.025488659508417714
    ],
    "projected_hold_object_drop_m": 0.24248932912195165,
    "projected_hold_hybrid_contact_group_count": 0.0,
    "projected_hold_hard_contact_group_count": 0.0,
    "projected_hold_has_thumb_opposition": 0.0,
    "projected_contact_group_count": 4.0,
    "projected_hard_contact_group_count": 1.0,
    "projected_has_thumb_opposition": 1.0,
    "projected_reach_object_facing_cos": 0.9226574436690702,
    "projected_reach_base_facing_cos": -0.12815330288067422,
    "projected_reach_downward_component": 0.7437607179507307,
    "projected_reach_min_arm_table_clearance_m": 0.41590138914698727,
    "projected_cylinder_palm_clearance_error_m": 0.0,
    "projected_cylinder_opposition_cos": -1.0,
    "projected_hold_cylinder_palm_clearance_error_m": 0.0,
    "projected_hold_cylinder_opposition_cos": -1.0,
    "projected_anchor_rmse_m": 0.07331443502201762,
    "projected_anchor_max_error_m": 0.0919676136103599,
    "projected_anchor_pairs": 5.0,
    "projected_anchor_assignment_norm_cost": 0.24387909587421697,
    "projected_anchor_assignment_method": 1.0,
    "retarget_method": "genhand_direct",
    "wrist_error_m": 0.0,
    "palm_error_m": 0.0,
    "tip_rmse_m": 0.0,
    "semantic_frame_error_deg": 0.0,
    "source_root_translation_gap_m": 0.03549374961133304,
    "source_wrist_error_m": 0.057773631441190985,
    "source_palm_error_m": 0.06527029958250526,
    "source_tip_rmse_m": 0.078248410991091,
    "source_site_rmse_m": 0.07388415025337787,
    "source_semantic_frame_error_deg": 26.798072367483396,
    "source_contact_hamming": 4.0,
    "source_contact_misses": 2.0,
    "source_extra_contacts": 2.0,
    "projected_matched_target_contacts": 3.0,
    "projected_required_target_contacts": 2.0,
    "projected_hard_contact_count": 1.0,
    "projected_hybrid_contact_count": 5.0,
    "projected_min_contact_distance_m": -0.0007836524899173299,
    "projected_total_penetration_m": 0.0,
    "projected_max_penetration_m": 0.0,
    "projected_object_translation_drift_m": 0.0542220532637734,
    "projected_object_rotation_drift_deg": 5.377019661149013,
    "projected_retreat_m": 0.008764604616405481,
    "projected_hand_open_blend": 0.31487234277748866,
    "projected_hold_object_translation_m": 0.2782766362733804,
    "projected_hold_object_rotation_deg": 13.658642293865428,
    "projected_hold_table_contact": 1.0,
    "projected_hold_matched_target_contacts": 0.0,
    "genhand_fc_loss": 0.0,
    "genhand_fc_net_wrench": 0.0,
    "genhand_fc_lin_ind": 0.959687538480764,
    "genhand_fc_intfc": 0.0,
    "genhand_cluster_candidate_count": 66.0,
    "genhand_cluster_score_mean": 0.002921777410543026,
    "genhand_target_anchor_rmse_m": 0.001195303009937131,
    "projection_score": 10.489513603448723,
    "teacher_cost": 3.6347582590458973,
    "optimizer_cost": 0.0014252829403895596
  },
  {
    "label_idx": 17,
    "valid_execution": false,
    "source_contact_mask_12": [
      0,
      0,
      0,
      1,
      0,
      1,
      0,
      1,
      0,
      1,
      0,
      1
    ],
    "projected_physical_contact_mask_12": [
      0,
      0,
      0,
      1,
      0,
      1,
      0,
      1,
      0,
      0,
      0,
      0
    ],
    "projected_proximity_contact_mask_12": [
      0,
      0,
      0,
      1,
      0,
      1,
      0,
      1,
      0,
      0,
      0,
      0
    ],
    "projected_contact_mask_12": [
      0,
      0,
      0,
      1,
      0,
      1,
      0,
      1,
      0,
      0,
      0,
      0
    ],
    "projected_contact_distance_12_m": [
      0.025500000000000002,
      0.015080523991130202,
      0.006958516226457378,
      -0.0012848032246343972,
      0.012876395839381088,
      -0.007503883733644518,
      0.006997392913573975,
      -0.006070818469050752,
      0.009957860145302047,
      0.008063928439203612,
      0.02266622022131366,
      0.02432223159819827
    ],
    "projected_hold_object_drop_m": 0.2462456308683833,
    "projected_hold_hybrid_contact_group_count": 0.0,
    "projected_hold_hard_contact_group_count": 0.0,
    "projected_hold_has_thumb_opposition": 0.0,
    "projected_contact_group_count": 3.0,
    "projected_hard_contact_group_count": 3.0,
    "projected_has_thumb_opposition": 1.0,
    "projected_reach_object_facing_cos": 0.9624047500681153,
    "projected_reach_base_facing_cos": -0.1326872098604579,
    "projected_reach_downward_component": 0.6942464762247761,
    "projected_reach_min_arm_table_clearance_m": 0.393383312055092,
    "projected_cylinder_palm_clearance_error_m": 0.0,
    "projected_cylinder_opposition_cos": -1.0,
    "projected_hold_cylinder_palm_clearance_error_m": 0.0,
    "projected_hold_cylinder_opposition_cos": -1.0,
    "projected_anchor_rmse_m": 0.07481278336858728,
    "projected_anchor_max_error_m": 0.08890652135194911,
    "projected_anchor_pairs": 5.0,
    "projected_anchor_assignment_norm_cost": 0.18066981562741888,
    "projected_anchor_assignment_method": 1.0,
    "retarget_method": "genhand_direct",
    "wrist_error_m": 0.0,
    "palm_error_m": 0.0,
    "tip_rmse_m": 0.0,
    "semantic_frame_error_deg": 0.0,
    "source_root_translation_gap_m": 0.03549375049881841,
    "source_wrist_error_m": 0.026351515797458872,
    "source_palm_error_m": 0.03330234926795831,
    "source_tip_rmse_m": 0.046658773094184675,
    "source_site_rmse_m": 0.04257540266542554,
    "source_semantic_frame_error_deg": 22.89364516891295,
    "source_contact_hamming": 2.0,
    "source_contact_misses": 2.0,
    "source_extra_contacts": 0.0,
    "projected_matched_target_contacts": 3.0,
    "projected_required_target_contacts": 2.0,
    "projected_hard_contact_count": 3.0,
    "projected_hybrid_contact_count": 3.0,
    "projected_min_contact_distance_m": -0.007503883733644518,
    "projected_total_penetration_m": 0.0,
    "projected_max_penetration_m": 0.0,
    "projected_object_translation_drift_m": 0.04107146784143211,
    "projected_object_rotation_drift_deg": 4.742549045405872,
    "projected_retreat_m": 0.020662716574531215,
    "projected_hand_open_blend": 0.3187988719451757,
    "projected_hold_object_translation_m": 0.2488710420796778,
    "projected_hold_object_rotation_deg": 6.183979563773881,
    "projected_hold_table_contact": 1.0,
    "projected_hold_matched_target_contacts": 0.0,
    "genhand_fc_loss": 0.0,
    "genhand_fc_net_wrench": 0.0,
    "genhand_fc_lin_ind": 0.9258639773881318,
    "genhand_fc_intfc": 0.0,
    "genhand_cluster_candidate_count": 70.0,
    "genhand_cluster_score_mean": 0.004190910399633637,
    "genhand_target_anchor_rmse_m": 0.0009313607170533373,
    "projection_score": 10.039473965145824,
    "teacher_cost": 3.4027493535499134,
    "optimizer_cost": 0.003010300169846176
  }
]